MANIFEST.in
README.rst
setup.py
version.txt
contrib/wireshark-curvecp.lua
spiral/__init__.py
spiral/dnscurve.py
spiral/keys.py
spiral/util.py
spiral.egg-info/PKG-INFO
spiral.egg-info/SOURCES.txt
spiral.egg-info/dependency_links.txt
spiral.egg-info/entry_points.txt
spiral.egg-info/not-zip-safe
spiral.egg-info/requires.txt
spiral.egg-info/top_level.txt
spiral/curvecp/__init__.py
spiral/curvecp/_c_libcurvecpr.py
spiral/curvecp/_curvecpm.py
spiral/curvecp/_libcurvecpr.py
spiral/curvecp/address.py
spiral/curvecp/errors.py
spiral/curvecp/util.py
spiral/curvecp/_pynacl/__init__.py
spiral/curvecp/_pynacl/_dna_pb2.py
spiral/curvecp/_pynacl/chicago.py
spiral/curvecp/_pynacl/endpoints.py
spiral/curvecp/_pynacl/interval.py
spiral/curvecp/_pynacl/message.py
spiral/curvecp/_pynacl/remy.py
spiral/curvecp/_pynacl/server.py
spiral/curvecp/_pynacl/transport.py
spiral/curvecp/_pynacl/test/__init__.py
spiral/curvecp/_pynacl/test/test_acceptance.py
spiral/curvecp/_pynacl/test/test_message.py
spiral/curvecp/_pynacl/test/test_transport.py
spiral/curvecp/_pynacl/test/util.py
spiral/scripts/__init__.py
spiral/scripts/curvecpmclient.py
spiral/scripts/curvecpmserver.py
spiral/test/__init__.py
spiral/test/test_acceptance.py
spiral/test/test_dnscurve.py
spiral/test/util.py