Metadata-Version: 1.1
Name: spiral
Version: 0.14.1.0
Summary: elliptic-curve-protected protocol implementations for twisted
Home-page: https://github.com/habnabit/spiral
Author: Aaron Gallagher
Author-email: _@habnab.it
License: ISC
Platform: UNKNOWN
Classifier: Development Status :: 2 - Pre-Alpha
Classifier: License :: OSI Approved :: ISC License (ISCL)
Classifier: Operating System :: OS Independent
Classifier: Programming Language :: Python :: 2
Classifier: Programming Language :: Python :: 2.7
Classifier: Topic :: Security
